pylabutils/__init__.py
pylabutils/_colors.py
pylabutils/_tools.py
pylabutils/_tools/__init__.py
pylabutils/_tools/_add_cols.py
pylabutils/_tools/_colors.py
pylabutils/_tools/_ffixx.py
pylabutils/_tools/_get_image.py
pylabutils/_tools/_imports.py
pylabutils/_tools/_ms_methods.py
pylabutils/numfit/__init__.py
pylabutils/numfit/fit.py
pylabutils/numfit/methods.py
pylabutils/numfit/methods/__init__.py
pylabutils/numfit/methods/_find_beta.py
pylabutils/numfit/methods/_odr_fit.py
pylabutils/numfit/methods/minimize/__init__.py
pylabutils/numfit/methods/minimize/_sqerr_sum.py
pylabutils/utils/Interval.py
pylabutils/utils/__init__.py
pylabutils/utils/io.py
pylabutils/utils/multisort.py
pylabutils/utils/operate.py
pylabutils/utils/io/__init__.py
pylabutils/utils/io/_plot_fit.py
pylabutils/utils/io/_print_measure.py
pylabutils/utils/io/read_data.py
pylabutils/utils/io/tex_table.py
pylabutils/utils/io/wdir.py
pylabutils-1.1.0.dist-info/LICENSE
pylabutils-1.1.0.dist-info/METADATA
pylabutils-1.1.0.dist-info/WHEEL
pylabutils-1.1.0.dist-info/top_level.txt
pylabutils-1.1.0.dist-info/RECORD
