Metadata-Version: 2.1
Name: pylabutils
Version: 1.1.0
Summary: Some utils for working with python in a simple lab-like environment
Home-page: https://github.com/mariogarcc/pylabutils
Author: Mario García
Author-email: mariogarcc@gmail.com
License: MIT
Keywords: laboratory utils tools
Platform: any
Classifier: Development Status :: 5 - Production/Stable
Classifier: Programming Language :: Python :: 3.7
Classifier: Intended Audience :: Science/Research
Classifier: Intended Audience :: Education
Classifier: Topic :: Utilities
Classifier: License :: OSI Approved :: MIT License
Classifier: Operating System :: OS Independent
Requires-Python: ~=3.7
Requires-Dist: ipython
Requires-Dist: numpy
Requires-Dist: matplotlib
Requires-Dist: scipy
Requires-Dist: uncertainties
